Workbook

Sheet LEIA-ME
A1: PROJECTO FINAL — Gestão Executiva de Oferta e Produto | Marketing Bancário
A3: Objectivo | B3: Construir uma solução completa em Excel + Power BI + IA para acompanhar performance de produtos, campanhas, canais, clientes, metas, cross-sell, adopção digital e KPIs executivos.
A4: Contexto | B4: Caso educacional avançado inspirado no contexto público do BAI e da banca de retalho angolana.
A5: Natureza dos dados | B5: Dados simulados e realistas; não representam dados internos, pessoais ou confidenciais do BAI.
A6: Entrega esperada | B6: Modelo estrela, medidas DAX, 4 páginas de dashboard, análise executiva e recomendações.
A7: Fonte pública | B7: https://www.bancobai.ao/media/tlhbe0uy/relatorio-e-contas-individual-e-consolidado-anual-2025.pdf
A9: Folha | B9: Função
A10: Dim_Clientes | B10: Base simulada de clientes e atributos de segmentação.
A11: Dim_Produtos | B11: Catálogo de produtos e pilares.
A12: Dim_Canais | B12: Canais de marketing/serviço.
A13: Calendario | B13: Dimensão mensal.
A14: Fact_Performance_Produto | B14: Performance mensal agregada por produto, segmento e província.
A15: Fact_Campanhas | B15: Funil e investimento de campanhas.
... A19: Dashboard_Base | B19: Resumo inicial para validação.

Sheet Dim_Clientes
A1: Cliente_ID | B1: Segmento | C1: Provincia | D1: Idade | E1: Genero | F1: Digital_Activo | G1: Salario_Domiciliado | H1: NPS | I1: Antiguidade_Meses | J1: Score_Risco
A2: C00001 | B2: Jovem Profissional | C2: Luanda | D2: 18 | E2: M | F2: Sim | G2: Sim | H2: 8 | I2: 23 | J2: 669
A3: C00002 | B3: Premium | C3: Luanda | D3: 48 | E3: M | F3: Sim | G3: Sim | H3: 7 | I3: 72 | J3: 790
A4: C00003 | B4: Assalariado | C4: Luanda | D4: 49 | E4: F | F4: Sim | G4: Sim | H4: 8 | I4: 109 | J4: 646
A5: C00004 | B5: Mass Market | C5: Huíla | D5: 28 | E5: F | F5: Sim | G5: Não | H5: 9 | I5: 164 | J5: 599
A6: C00005 | B6: Mass Market | C6: Luanda | D6: 48 | E6: F | F6: Não | G6: Não | H6: 4 | I6: 128 | J6: 582
A7: C00006 | B7: ENI | C7: Huambo | D7: 25 | E7: M | F7: Sim | G7: Não | H7: 6 | I7: 10 | J7: 710
A8: C00007 | B8: Assalariado | C8: Huíla | D8: 22 | E8: F | F8: Sim | G8: Sim | H8: 8 | I8: 137 | J8: 752
A9: C00008 | B9: Jovem Profissional | C9: Huíla | D9: 47 | E9: F | F9: Sim | G9: Não | H9: 4 | I9: 26 | J9: 634
A10: C00009 | B10: ENI | C10: Huíla | D10: 22 | E10: M | F10: Sim | G10: Não | H10: 9 | I10: 97 | J10: 708
A11: C00010 | B11: ENI | C11: Luanda | D11: 48 | E11: F | F11: Não | G11: Não | H11: 10 | I11: 89 | J11: 614
A12: C00011 | B12: Jovem Profissional | C12: Luanda | D12: 27 | E12: M | F12: Sim | G12: Sim | H12: 6 | I12: 109 | J12: 735
A13: C00012 | B13: ENI | C13: Luanda | D13: 39 | E13: M | F13: Sim | G13: Não | H13: 8 | I13: 147 | J13: 739
... A2001: C02000 | B2001: Mass Market | C2001: Luanda | D2001: 23 | E2001: F | F2001: Sim | G2001: Não | H2001: 10 | I2001: 164 | J2001: 560

Sheet Dim_Produtos
A1: Produto_ID | B1: Produto | C1: Categoria | D1: Pilar | E1: Prioridade
A2: P001 | B2: Conta à Ordem | C2: Conta | D2: Relacionamento | E2: Base
A3: P002 | B3: BAI Directo | C3: Canal Digital | D3: Digital | E3: Base
A4: P003 | B4: Cartão Multicaixa | C4: Cartão | D4: Transacional | E4: Base
A5: P004 | B5: Cartão de Crédito | C5: Cartão | D5: Crédito | E5: Complementar
A6: P005 | B6: Crédito Pessoal Online | C6: Crédito | D6: Crédito | E6: Estratégico
A7: P006 | B7: Crédito Salário | C7: Crédito | D7: Crédito | E7: Complementar
A8: P007 | B8: Depósito a Prazo | C8: Poupança/Investimento | D8: Poupança | E8: Estratégico
A9: P008 | B9: Seguro Protecção | C9: Seguro | D9: Protecção | E9: Complementar
A10: P009 | B10: Domiciliação de Salário | C10: Serviço | D10: Relacionamento | E10: Estratégico
A11: P010 | B11: BAI Paga / QR | C11: Pagamento | D11: Digital | E11: Complementar
A12: P011 | B12: Conta BAI Jovem | C12: Conta | D12: Aquisição | E12: Estratégico
A13: P012 | B13: Solução Premium | C13: Pacote | D13: Relacionamento | E13: Estratégico

Sheet Dim_Canais
A1: Canal_ID | B1: Canal | C1: Tipo_Canal
A2: CH01 | B2: Balcão | C2: Presencial
A3: CH02 | B3: BAI Directo | C3: Digital
A4: CH03 | B4: Agente Bancário | C4: Presencial Assistido
A5: CH04 | B5: Meta Ads | C5: Digital Pago
A6: CH05 | B6: Google Ads | C6: Digital Pago
A7: CH06 | B7: SMS | C7: Direct Marketing
A8: CH07 | B8: E-mail | C8: Direct Marketing
A9: CH08 | B9: Gestor | C9: Relacionamento

Sheet Calendario
A1: Mes | B1: Ano | C1: Numero_Mes | D1: Nome_Mes | E1: Trimestre | F1: AnoMes
A2: 45658 | B2: 2025 | C2: 1 | D2: Jan | E2: T1 | F2: 2025-01
A3: 45689 | B3: 2025 | C3: 2 | D3: Feb | E3: T1 | F3: 2025-02
A4: 45717 | B4: 2025 | C4: 3 | D4: Mar | E4: T1 | F4: 2025-03
A5: 45748 | B5: 2025 | C5: 4 | D5: Apr | E5: T2 | F5: 2025-04
A6: 45778 | B6: 2025 | C6: 5 | D6: May | E6: T2 | F6: 2025-05
A7: 45809 | B7: 2025 | C7: 6 | D7: Jun | E7: T2 | F7: 2025-06
A8: 45839 | B8: 2025 | C8: 7 | D8: Jul | E8: T3 | F8: 2025-07
A9: 45870 | B9: 2025 | C9: 8 | D9: Aug | E9: T3 | F9: 2025-08
A10: 45901 | B10: 2025 | C10: 9 | D10: Sep | E10: T3 | F10: 2025-09
A11: 45931 | B11: 2025 | C11: 10 | D11: Oct | E11: T4 | F11: 2025-10
A12: 45962 | B12: 2025 | C12: 11 | D12: Nov | E12: T4 | F12: 2025-11
A13: 45992 | B13: 2025 | C13: 12 | D13: Dec | E13: T4 | F13: 2025-12
... A21: 46235 | B21: 2026 | C21: 8 | D21: Aug | E21: T3 | F21: 2026-08

Sheet Fact_Performance_Produto
A1: Fact_ID | B1: Mes | C1: Produto_ID | D1: Segmento | E1: Provincia | F1: Clientes_Activos | G1: Novas_Adesoes | H1: Churn_Clientes | I1: Transacoes | J1: Volume_AOA | K1: Saldo_Medio_Total_AOA | L1: Receita_Estimada_AOA
A2: FP0000001 | B2: 45658 | C2: P001 | D2: Mass Market | E2: Luanda | F2: 506 | G2: 42 | H2: 7 | I2: 7907 | J2: 1.1412502e+09 | K2: 6.9006082e+08 | L2: 1597750.2
A3: FP0000002 | B3: 45658 | C3: P001 | D3: Mass Market | E3: Benguela | F3: 165 | G3: 9 | H3: 3 | I3: 2345 | J3: 3.5275311e+08 | K3: 3.0166038e+08 | L3: 493854.35
A4: FP0000003 | B4: 45658 | C4: P001 | D4: Mass Market | E4: Huíla | F4: 142 | G4: 11 | H4: 5 | I4: 2565 | J4: 3.154715e+08 | K4: 1.126343e+08 | L4: 441660.1
A5: FP0000004 | B5: 45658 | C5: P001 | D5: Mass Market | E5: Huambo | F5: 115 | G5: 5 | H5: 4 | I5: 2207 | J5: 3.6415585e+08 | K5: 2.3160643e+08 | L5: 509818.19
A6: FP0000005 | B6: 45658 | C6: P001 | D6: Mass Market | E6: Cabinda | F6: 77 | G6: 7 | H6: 1 | I6: 1396 | J6: 1.8182825e+08 | K6: 1.5611356e+08 | L6: 254559.56
A7: FP0000006 | B7: 45658 | C7: P001 | D7: Mass Market | E7: Cuanza Sul | F7: 84 | G7: 7 | H7: 2 | I7: 1222 | J7: 1.8291066e+08 | K7: 1.5947967e+08 | L7: 256074.92
A8: FP0000007 | B8: 45658 | C8: P001 | D8: Assalariado | E8: Luanda | F8: 476 | G8: 39 | H8: 11 | I8: 8045 | J8: 1.2749543e+09 | K8: 9.1949111e+08 | L8: 1784936
A9: FP0000008 | B9: 45658 | C9: P001 | D9: Assalariado | E9: Benguela | F9: 168 | G9: 10 | H9: 2 | I9: 3173 | J9: 4.0965262e+08 | K9: 3.059146e+08 | L9: 573513.67
A10: FP0000009 | B10: 45658 | C10: P001 | D10: Assalariado | E10: Huíla | F10: 124 | G10: 7 | H10: 1 | I10: 1808 | J10: 2.3663034e+08 | K10: 63215283 | L10: 331282.47
A11: FP0000010 | B11: 45658 | C11: P001 | D11: Assalariado | E11: Huambo | F11: 114 | G11: 6 | H11: 1 | I11: 1641 | J11: 2.4415619e+08 | K11: 45185390 | L11: 341818.67
A12: FP0000011 | B12: 45658 | C12: P001 | D12: Assalariado | E12: Cabinda | F12: 76 | G12: 3 | H12: 2 | I12: 1417 | J12: 2.1655647e+08 | K12: 74956327 | L12: 303179.06
A13: FP0000012 | B13: 45658 | C13: P001 | D13: Assalariado | E13: Cuanza Sul | F13: 78 | G13: 5 | H13: 3 | I13: 1426 | J13: 2.0261187e+08 | K13: 1.1240127e+08 | L13: 283656.61
... A8641: FP0008640 | B8641: 46235 | C8641: P012 | D8641: Microempresa | E8641: Cuanza Sul | F8641: 2 | G8641: 0 | H8641: 0 | I8641: 13 | J8641: 3899229.4 | K8641: 1404679.9 | L8641: 13647.3

Sheet Fact_Campanhas
A1: Campanha_ID | B1: Mes | C1: Campanha | D1: Canal_ID | E1: Segmento | F1: Produto_ID | G1: Impressoes | H1: Cliques | I1: Leads | J1: Conversoes | K1: Investimento_AOA | L1: CTR | M1: Conv_Lead | N1: CPL_AOA | O1: CPA_AOA
A2: FC000001 | B2: 46174 | C2: Poupança Inteligente | D2: CH04 | E2: Premium | F2: P005 | G2: 85995 | H2: 1604 | I2: 247 | J2: 84 | K2: 2242847.9 | L2: =IFERROR(H2/G2,0) -> 0.018652247 | M2: =IFERROR(J2/I2,0) -> 0.34008097 | N2: =IFERROR(K2/I2,0) -> 9080.3558 | O2: =IFERROR(K2/J2,0) -> 26700.57
A3: FC000002 | B3: 46235 | C3: Domiciliação 360 | D3: CH04 | E3: Assalariado | F3: P007 | G3: 24943 | H3: 1416 | I3: 344 | J3: 198 | K3: 1878137.3 | L3: =IFERROR(H3/G3,0) -> 0.056769434 | M3: =IFERROR(J3/I3,0) -> 0.5755814 | N3: =IFERROR(K3/I3,0) -> 5459.7013 | O3: =IFERROR(K3/J3,0) -> 9485.5417
A4: FC000003 | B4: 45839 | C4: BAI Directo Activação | D4: CH05 | E4: Mass Market | F4: P002 | G4: 22193 | H4: 1623 | I4: 245 | J4: 126 | K4: 2576245.2 | L4: =IFERROR(H4/G4,0) -> 0.073131167 | M4: =IFERROR(J4/I4,0) -> 0.51428571 | N4: =IFERROR(K4/I4,0) -> 10515.287 | O4: =IFERROR(K4/J4,0) -> 20446.391
A5: FC000004 | B5: 45778 | C5: Aquisição Digital | D5: CH04 | E5: ENI | F5: P007 | G5: 27752 | H5: 1838 | I5: 225 | J5: 77 | K5: 1720495.6 | L5: =IFERROR(H5/G5,0) -> 0.066229461 | M5: =IFERROR(J5/I5,0) -> 0.34222222 | N5: =IFERROR(K5/I5,0) -> 7646.647 | O5: =IFERROR(K5/J5,0) -> 22344.098
A6: FC000005 | B6: 46204 | C6: Domiciliação 360 | D6: CH06 | E6: Premium | F6: P011 | G6: 82618 | H6: 3789 | I6: 886 | J6: 424 | K6: 593935.73 | L6: =IFERROR(H6/G6,0) -> 0.045861677 | M6: =IFERROR(J6/I6,0) -> 0.4785553 | N6: =IFERROR(K6/I6,0) -> 670.35635 | O6: =IFERROR(K6/J6,0) -> 1400.7918
A7: FC000006 | B7: 45748 | C7: BAI Directo Activação | D7: CH06 | E7: Assalariado | F7: P005 | G7: 34418 | H7: 2517 | I7: 515 | J7: 215 | K7: 272017.87 | L7: =IFERROR(H7/G7,0) -> 0.073130339 | M7: =IFERROR(J7/I7,0) -> 0.41747573 | N7: =IFERROR(K7/I7,0) -> 528.19004 | O7: =IFERROR(K7/J7,0) -> 1265.1994
A8: FC000007 | B8: 46143 | C8: Poupança Inteligente | D8: CH04 | E8: Microempresa | F8: P009 | G8: 101389 | H8: 7410 | I8: 1233 | J8: 713 | K8: 2061573.8 | L8: =IFERROR(H8/G8,0) -> 0.073084851 | M8: =IFERROR(J8/I8,0) -> 0.5782644 | N8: =IFERROR(K8/I8,0) -> 1671.9982 | O8: =IFERROR(K8/J8,0) -> 2891.4078
A9: FC000008 | B9: 45962 | C9: Jovem Digital | D9: CH05 | E9: Mass Market | F9: P005 | G9: 109777 | H9: 7129 | I9: 1113 | J9: 588 | K9: 2605562.1 | L9: =IFERROR(H9/G9,0) -> 0.064940744 | M9: =IFERROR(J9/I9,0) -> 0.52830189 | N9: =IFERROR(K9/I9,0) -> 2341.0262 | O9: =IFERROR(K9/J9,0) -> 4431.2281
A10: FC000009 | B10: 45931 | C10: BAI Directo Activação | D10: CH04 | E10: Jovem Profissional | F10: P004 | G10: 85278 | H10: 4697 | I10: 1104 | J10: 547 | K10: 2986830.1 | L10: =IFERROR(H10/G10,0) -> 0.055078684 | M10: =IFERROR(J10/I10,0) -> 0.49547101 | N10: =IFERROR(K10/I10,0) -> 2705.462 | O10: =IFERROR(K10/J10,0) -> 5460.384
A11: FC000010 | B11: 46023 | C11: BAI Directo Activação | D11: CH06 | E11: Jovem Profissional | F11: P007 | G11: 44740 | H11: 712 | I11: 141 | J11: 70 | K11: 3187911.7 | L11: =IFERROR(H11/G11,0) -> 0.015914171 | M11: =IFERROR(J11/I11,0) -> 0.4964539 | N11: =IFERROR(K11/I11,0) -> 22609.303 | O11: =IFERROR(K11/J11,0) -> 45541.596
A12: FC000011 | B12: 46143 | C12: Aquisição Digital | D12: CH06 | E12: Jovem Profissional | F12: P004 | G12: 82867 | H12: 1888 | I12: 332 | J12: 127 | K12: 402750.37 | L12: =IFERROR(H12/G12,0) -> 0.022783496 | M12: =IFERROR(J12/I12,0) -> 0.38253012 | N12: =IFERROR(K12/I12,0) -> 1213.1035 | O12: =IFERROR(K12/J12,0) -> 3171.2628
A13: FC000012 | B13: 46174 | C13: Poupança Inteligente | D13: CH04 | E13: Mass Market | F13: P002 | G13: 34534 | H13: 1296 | I13: 184 | J13: 92 | K13: 1981191.9 | L13: =IFERROR(H13/G13,0) -> 0.037528233 | M13: =IFERROR(J13/I13,0) -> 0.5 | N13: =IFERROR(K13/I13,0) -> 10767.347 | O13: =IFERROR(K13/J13,0) -> 21534.694
... A1001: FC001000 | B1001: 45870 | C1001: Jovem Digital | D1001: CH06 | E1001: Assalariado | F1001: P007 | G1001: 89750 | H1001: 2087 | I1001: 208 | J1001: 66 | K1001: 1766211 | L1001: =IFERROR(H1001/G1001,0) -> 0.023253482 | M1001: =IFERROR(J1001/I1001,0) -> 0.31730769 | N1001: =IFERROR(K1001/I1001,0) -> 8491.3991 | O1001: =IFERROR(K1001/J1001,0) -> 26760.773

Sheet Fact_CrossSell
A1: Oportunidade_ID | B1: Mes | C1: Cliente_ID | D1: Segmento | E1: Provincia | F1: Oferta_CrossSell | G1: Produto_Alvo_ID | H1: Elegivel | I1: Contactado | J1: Aceitou | K1: Valor_Potencial_AOA
A2: CS000001 | B2: 46174 | C2: C00088 | D2: Assalariado | E2: Luanda | F2: BAI Directo→CPO | G2: P005 | H2: Sim | I2: Sim | J2: Não | K2: 0
A3: CS000002 | B3: 46082 | C3: C01659 | D3: Jovem Profissional | E3: Luanda | F3: Jovem→Conta BAI Jovem | G3: P011 | H3: Não | I3: Sim | J3: Não | K3: 0
A4: CS000003 | B4: 46113 | C4: C01559 | D4: Assalariado | E4: Cuanza Sul | F4: Conta→BAI Directo | G4: P002 | H4: Sim | I4: Sim | J4: Não | K4: 0
A5: CS000004 | B5: 46113 | C5: C01590 | D5: Assalariado | E5: Huíla | F5: Conta→BAI Directo | G5: P002 | H5: Não | I5: Não | J5: Não | K5: 0
A6: CS000005 | B6: 46054 | C6: C00344 | D6: Mass Market | E6: Luanda | F6: Assalariado→Domiciliação | G6: P009 | H6: Não | I6: Sim | J6: Não | K6: 0
A7: CS000006 | B7: 46204 | C7: C01509 | D7: Mass Market | E7: Luanda | F7: Conta→BAI Directo | G7: P002 | H7: Não | I7: Sim | J7: Não | K7: 0
A8: CS000007 | B8: 46054 | C8: C01476 | D8: Mass Market | E8: Luanda | F8: BAI Directo→CPO | G8: P005 | H8: Sim | I8: Não | J8: Não | K8: 0
A9: CS000008 | B9: 46174 | C9: C01909 | D9: Assalariado | E9: Huíla | F9: Salário→Crédito Salário | G9: P006 | H9: Sim | I9: Não | J9: Não | K9: 0
A10: CS000009 | B10: 46204 | C10: C01377 | D10: Jovem Profissional | E10: Cabinda | F10: BAI Directo→CPO | G10: P005 | H10: Sim | I10: Sim | J10: Não | K10: 0
A11: CS000010 | B11: 46054 | C11: C00590 | D11: Mass Market | E11: Luanda | F11: Conta→Cartão | G11: P003 | H11: Não | I11: Sim | J11: Não | K11: 0
A12: CS000011 | B12: 46113 | C12: C00283 | D12: Assalariado | E12: Luanda | F12: BAI Directo→CPO | G12: P005 | H12: Sim | I12: Sim | J12: Sim | K12: 3646271
A13: CS000012 | B13: 46204 | C13: C01664 | D13: Mass Market | E13: Luanda | F13: BAI Directo→CPO | G13: P005 | H13: Sim | I13: Sim | J13: Sim | K13: 3451813
... A2401: CS002400 | B2401: 46113 | C2401: C01546 | D2401: Jovem Profissional | E2401: Luanda | F2401: Conta→Seguro | G2401: P008 | H2401: Sim | I2401: Sim | J2401: Não | K2401: 0

Sheet Metas_KPI
A1: Mes | B1: Produto_ID | C1: Meta_Clientes_Activos | D1: Meta_Churn_Max | E1: Meta_Taxa_CrossSell | F1: Meta_Volume_AOA | G1: Meta_Receita_AOA
A2: 45658 | B2: P001 | C2: 2000 | D2: 0.0412 | E2: 0.2802 | F2: 843821024 | G2: 54250025
A3: 45658 | B3: P002 | C3: 1600 | D3: 0.0289 | E3: 0.3607 | F3: 445983429 | G3: 73995425
A4: 45658 | B4: P003 | C4: 1850 | D4: 0.0406 | E4: 0.2276 | F4: 338475973 | G4: 9374974
A5: 45658 | B5: P004 | C5: 330 | D5: 0.0186 | E5: 0.2807 | F5: 874648321 | G5: 33053882
A6: 45658 | B6: P005 | C6: 480 | D6: 0.0195 | E6: 0.2315 | F6: 847607279 | G6: 45524238
A7: 45658 | B7: P006 | C7: 390 | D7: 0.0187 | E7: 0.289 | F7: 114528697 | G7: 52313408
A8: 45658 | B8: P007 | C8: 600 | D8: 0.0411 | E8: 0.1806 | F8: 186295266 | G8: 18586621
A9: 45658 | B9: P008 | C9: 460 | D9: 0.0217 | E9: 0.1836 | F9: 423338344 | G9: 67797538
A10: 45658 | B10: P009 | C10: 820 | D10: 0.028 | E10: 0.2875 | F10: 345618084 | G10: 36917420
A11: 45658 | B11: P010 | C11: 300 | D11: 0.0242 | E11: 0.2021 | F11: 1000432802 | G11: 33907861
A12: 45658 | B12: P011 | C12: 400 | D12: 0.0306 | E12: 0.3571 | F12: 896931337 | G12: 30069448
A13: 45658 | B13: P012 | C13: 145 | D13: 0.0301 | E13: 0.2305 | F13: 427056653 | G13: 26097296
... A241: 46235 | B241: P012 | C241: 172 | D241: 0.0361 | E241: 0.3937 | F241: 406772287 | G241: 25061931

Sheet Dicionario_KPI
A1: KPI | B1: Fórmula | C1: Uso
A2: Clientes Activos | B2: SUM ou DISTINCTCOUNT conforme a tabela | C2: Base utilizadora.
A3: Novas Adesões | B3: SUM(Novas_Adesoes) | C3: Aquisição/crescimento.
A4: Churn Rate | B4: Churn / Clientes Activos | C4: Retenção.
A5: Penetração | B5: Clientes do Produto / Clientes do Segmento | C5: Potencial de oferta.
A6: Produtos por Cliente | B6: Relações activas / clientes | C6: Profundidade.
A7: Adopção Digital | B7: Clientes digitais / total clientes | C7: Migração digital.
A8: CTR | B8: Cliques / Impressões | C8: Eficácia de comunicação.
A9: Conversão Leads | B9: Conversões / Leads | C9: Eficiência de funil.
A10: CPL | B10: Investimento / Leads | C10: Custo por lead.
A11: CPA | B11: Investimento / Conversões | C11: Custo por aquisição.
A12: Taxa Cross-sell | B12: Aceites / Contactados | C12: Eficiência de oferta adicional.
... A14: Atingimento de Meta | B14: Realizado / Meta | C14: Gestão executiva.

Sheet Dashboard_Base
A1: Dashboard Base — Projecto Final
A3: KPI | B3: Valor | C3: Leitura | E3: Mês | F3: Clientes Activos | G3: Novas Adesões | H3: Churn | I3: Receita Estimada
A4: Clientes no Cadastro | B4: =COUNTA(Dim_Clientes!A2:A2001) -> 2000 | C4: Tamanho da base. | E4: 46023 | F4: =SUMIFS(Fact_Performance_Produto!$F$2:$F$8641,Fact_Performance_Produto!$B$2:$B$8641,E4) -> 19748 | G4: =SUMIFS(Fact_Performance_Produto!$G$2:$G$8641,Fact_Performance_Produto!$B$2:$B$8641,E4) -> 1255 | H4: =SUMIFS(Fact_Performance_Produto!$H$2:$H$8641,Fact_Performance_Produto!$B$2:$B$8641,E4) -> 462 | I4: =SUMIFS(Fact_Performance_Produto!$L$2:$L$8641,Fact_Performance_Produto!$B$2:$B$8641,E4) -> 96697634
A5: Clientes Digitais | B5: =COUNTIF(Dim_Clientes!F2:F2001,"Sim") -> 1488 | C5: Clientes já activos digitalmente. | E5: 46054 | F5: =SUMIFS(Fact_Performance_Produto!$F$2:$F$8641,Fact_Performance_Produto!$B$2:$B$8641,E5) -> 20218 | G5: =SUMIFS(Fact_Performance_Produto!$G$2:$G$8641,Fact_Performance_Produto!$B$2:$B$8641,E5) -> 1336 | H5: =SUMIFS(Fact_Performance_Produto!$H$2:$H$8641,Fact_Performance_Produto!$B$2:$B$8641,E5) -> 429 | I5: =SUMIFS(Fact_Performance_Produto!$L$2:$L$8641,Fact_Performance_Produto!$B$2:$B$8641,E5) -> 1.0110332e+08
A6: Adopção Digital | B6: =B5/B4 -> 0.744 | C6: Percentagem da base digital. | E6: 46082 | F6: =SUMIFS(Fact_Performance_Produto!$F$2:$F$8641,Fact_Performance_Produto!$B$2:$B$8641,E6) -> 20382 | G6: =SUMIFS(Fact_Performance_Produto!$G$2:$G$8641,Fact_Performance_Produto!$B$2:$B$8641,E6) -> 1263 | H6: =SUMIFS(Fact_Performance_Produto!$H$2:$H$8641,Fact_Performance_Produto!$B$2:$B$8641,E6) -> 492 | I6: =SUMIFS(Fact_Performance_Produto!$L$2:$L$8641,Fact_Performance_Produto!$B$2:$B$8641,E6) -> 1.0021567e+08
A7: Conversões de Campanha | B7: =SUM(Fact_Campanhas!J2:J1001) -> 203866 | C7: Resultado de marketing. | E7: 46113 | F7: =SUMIFS(Fact_Performance_Produto!$F$2:$F$8641,Fact_Performance_Produto!$B$2:$B$8641,E7) -> 20360 | G7: =SUMIFS(Fact_Performance_Produto!$G$2:$G$8641,Fact_Performance_Produto!$B$2:$B$8641,E7) -> 1258 | H7: =SUMIFS(Fact_Performance_Produto!$H$2:$H$8641,Fact_Performance_Produto!$B$2:$B$8641,E7) -> 465 | I7: =SUMIFS(Fact_Performance_Produto!$L$2:$L$8641,Fact_Performance_Produto!$B$2:$B$8641,E7) -> 1.0217477e+08
A8: Investimento em Campanhas | B8: =SUM(Fact_Campanhas!K2:K1001) -> 1.6818529e+09 | C8: Custo total de marketing. | E8: 46143 | F8: =SUMIFS(Fact_Performance_Produto!$F$2:$F$8641,Fact_Performance_Produto!$B$2:$B$8641,E8) -> 20513 | G8: =SUMIFS(Fact_Performance_Produto!$G$2:$G$8641,Fact_Performance_Produto!$B$2:$B$8641,E8) -> 1278 | H8: =SUMIFS(Fact_Performance_Produto!$H$2:$H$8641,Fact_Performance_Produto!$B$2:$B$8641,E8) -> 471 | I8: =SUMIFS(Fact_Performance_Produto!$L$2:$L$8641,Fact_Performance_Produto!$B$2:$B$8641,E8) -> 1.0058662e+08
A9: Cross-sell Aceites | B9: =COUNTIF(Fact_CrossSell!J2:J2401,"Sim") -> 385 | C9: Conversões de ofertas complementares. | E9: 46174 | F9: =SUMIFS(Fact_Performance_Produto!$F$2:$F$8641,Fact_Performance_Produto!$B$2:$B$8641,E9) -> 20996 | G9: =SUMIFS(Fact_Performance_Produto!$G$2:$G$8641,Fact_Performance_Produto!$B$2:$B$8641,E9) -> 1267 | H9: =SUMIFS(Fact_Performance_Produto!$H$2:$H$8641,Fact_Performance_Produto!$B$2:$B$8641,E9) -> 461 | I9: =SUMIFS(Fact_Performance_Produto!$L$2:$L$8641,Fact_Performance_Produto!$B$2:$B$8641,E9) -> 1.0371954e+08
E10: 46204 | F10: =SUMIFS(Fact_Performance_Produto!$F$2:$F$8641,Fact_Performance_Produto!$B$2:$B$8641,E10) -> 21128 | G10: =SUMIFS(Fact_Performance_Produto!$G$2:$G$8641,Fact_Performance_Produto!$B$2:$B$8641,E10) -> 1334 | H10: =SUMIFS(Fact_Performance_Produto!$H$2:$H$8641,Fact_Performance_Produto!$B$2:$B$8641,E10) -> 460 | I10: =SUMIFS(Fact_Performance_Produto!$L$2:$L$8641,Fact_Performance_Produto!$B$2:$B$8641,E10) -> 1.0813706e+08
E11: 46235 | F11: =SUMIFS(Fact_Performance_Produto!$F$2:$F$8641,Fact_Performance_Produto!$B$2:$B$8641,E11) -> 21355 | G11: =SUMIFS(Fact_Performance_Produto!$G$2:$G$8641,Fact_Performance_Produto!$B$2:$B$8641,E11) -> 1336 | H11: =SUMIFS(Fact_Performance_Produto!$H$2:$H$8641,Fact_Performance_Produto!$B$2:$B$8641,E11) -> 479 | I11: =SUMIFS(Fact_Performance_Produto!$L$2:$L$8641,Fact_Performance_Produto!$B$2:$B$8641,E11) -> 1.0316784e+08
